trif_trajectory/__init__.py
trif_trajectory/bootstrap.cpython-39-i386-linux-gnu.so
trif_trajectory-0.0.3.dist-info/WHEEL
trif_trajectory-0.0.3.dist-info/RECORD
trif_trajectory-0.0.3.dist-info/top_level.txt
trif_trajectory-0.0.3.dist-info/METADATA
