Metadata-Version: 2.1
Name: trif-trajectory
Version: 0.0.3
Summary: TRIF Trajectory
Author: Kan Liu
Author-email: liuk@wipm.ac.cn
Requires-Python: >=3.6
Requires-Dist: numpy
Requires-Dist: nonstationarity
Requires-Dist: scipy
Requires-Dist: plotly
Requires-Dist: pandas
Requires-Dist: panel
Requires-Dist: lmfit
Requires-Dist: param
